server.py
mcp_vibe_tools-3.0.2.dist-info/METADATA
mcp_vibe_tools-3.0.2.dist-info/WHEEL
mcp_vibe_tools-3.0.2.dist-info/entry_points.txt
mcp_vibe_tools-3.0.2.dist-info/top_level.txt
mcp_vibe_tools-3.0.2.dist-info/RECORD
