Metadata-Version: 2.4
Name: mcp-vibe-tools
Version: 3.0.2
Summary: MCP server for cursor-tools/cursor-tools
License: MIT
Requires-Python: >=3.10
Requires-Dist: mcp[cli]>=1.6.0
Provides-Extra: dev
Requires-Dist: tox; extra == "dev"
Requires-Dist: tox-gh-actions; extra == "dev"
Requires-Dist: build; extra == "dev"
Requires-Dist: wheel; extra == "dev"
Requires-Dist: twine; extra == "dev"
Requires-Dist: requests; extra == "dev"
